fossbot_lib/common/data_structures/__init__.py
fossbot_lib/common/data_structures/configuration.py
fossbot_lib/common/interfaces/__init__.py
fossbot_lib/common/interfaces/control_interfaces.py
fossbot_lib/common/interfaces/robot_interface.py
fossbot_lib/common/interfaces/sim_gym_interface.py
fossbot_lib/coppeliasim_robot/__init__.py
fossbot_lib/coppeliasim_robot/control.py
fossbot_lib/coppeliasim_robot/fossbot.py
fossbot_lib/coppeliasim_robot/sim.py
fossbot_lib/coppeliasim_robot/simConst.py
fossbot_lib/coppeliasim_robot/sim_gym.py
fossbot_lib/parameters_parser/__init__.py
fossbot_lib/parameters_parser/parser.py
fossbot_lib-0.1.3.6.dist-info/METADATA
fossbot_lib-0.1.3.6.dist-info/WHEEL
fossbot_lib-0.1.3.6.dist-info/top_level.txt
fossbot_lib-0.1.3.6.dist-info/RECORD
