Metadata-Version: 2.1
Name: fossbot-lib
Version: 0.1.3.6
Summary: FossBot Simulator Library
Home-page: UNKNOWN
Author: Christos Chronis & Manousos Linardakis
Author-email: chronis@hua.gr
License: UNKNOWN
Platform: UNKNOWN
